setup.cfg
setup.py
in_limbo/__init__.py
in_limbo/in_limbo_interfaces.py
in_limbo/sandwich_estimators.py
in_limbo/setup.py
in_limbo.egg-info/PKG-INFO
in_limbo.egg-info/SOURCES.txt
in_limbo.egg-info/dependency_links.txt
in_limbo.egg-info/top_level.txt
in_limbo/workflows/__init__.py
in_limbo/workflows/sandwich_workflows.py
in_limbo/workflows/setup.py