Metadata-Version: 1.0
Name: in-limbo
Version: 0.1.1
Summary: Sandwich estimation for fMRI
Home-page: http://www.gillesdehollander.nl
Author: Gilles de Hollander
Author-email: g.dehollander@uva.nl
License: UNKNOWN
Platform: UNKNOWN
